{
    "source" : ["./Plugins/VST3/PlugData.vst3/Contents/MacOS/PlugData", "./Plugins/AU/PlugData.component/Contents/MacOS/PlugData", "./Plugins/Standalone/PlugData.app/Contents/MacOS/PlugData", "./Plugins/LV2/PlugData.lv2/libPlugData.so"],
    "bundle_id" : "com.Octagon.PlugData",
    "apple_id": {
            "username" : "timschoen123@gmail.com",
            "password":  "@env:AC_PASSWORD"
    },
    "sign" : {
        "application_identity" : "Developer ID Application: Timothy Schoen (7SV7JPRR2L)"
    }
}
